studydrive/__init__.py
studydrive/studydriveapi.py
studydrive-0.3.2.dist-info/LICENSE
studydrive-0.3.2.dist-info/METADATA
studydrive-0.3.2.dist-info/WHEEL
studydrive-0.3.2.dist-info/top_level.txt
studydrive-0.3.2.dist-info/RECORD
