Metadata-Version: 2.1
Name: studydrive
Version: 0.3.2
Summary: A Python Wrapper for the (unofficial) Studydrive API
Home-page: https://github.com/henrydatei/studydrive-api
Author: Henry Haustein
License: UNKNOWN
Platform: UNKNOWN
Requires-Python: >=3.6
License-File: LICENSE
Requires-Dist: datetime
Requires-Dist: requests
